remoulade/__init__.py
remoulade/__main__.py
remoulade/actor.py
remoulade/broker.py
remoulade/collection_results.py
remoulade/common.py
remoulade/composition.py
remoulade/encoder.py
remoulade/errors.py
remoulade/generic.py
remoulade/logging.py
remoulade/message.py
remoulade/py.typed
remoulade/result.py
remoulade/utils.py
remoulade/worker.py
remoulade/api/__init__.py
remoulade/api/apispec.py
remoulade/api/main.py
remoulade/api/scheduler.py
remoulade/api/state.py
remoulade/brokers/__init__.py
remoulade/brokers/local.py
remoulade/brokers/rabbitmq.py
remoulade/brokers/stub.py
remoulade/cancel/__init__.py
remoulade/cancel/backend.py
remoulade/cancel/errors.py
remoulade/cancel/middleware.py
remoulade/cancel/backends/__init__.py
remoulade/cancel/backends/redis.py
remoulade/cancel/backends/stub.py
remoulade/cli/__init__.py
remoulade/cli/remoulade_ls.py
remoulade/cli/remoulade_run.py
remoulade/cli/remoulade_scheduler.py
remoulade/concurrent/__init__.py
remoulade/concurrent/backend.py
remoulade/concurrent/errors.py
remoulade/concurrent/lease.py
remoulade/concurrent/middleware.py
remoulade/concurrent/backends/__init__.py
remoulade/concurrent/backends/redis.py
remoulade/concurrent/backends/stub.py
remoulade/helpers/__init__.py
remoulade/helpers/actor_arguments.py
remoulade/helpers/backoff.py
remoulade/helpers/queues.py
remoulade/helpers/redis_client.py
remoulade/helpers/reduce.py
remoulade/middleware/__init__.py
remoulade/middleware/age_limit.py
remoulade/middleware/catch_error.py
remoulade/middleware/current_message.py
remoulade/middleware/heartbeat.py
remoulade/middleware/logging_metadata.py
remoulade/middleware/max_memory.py
remoulade/middleware/max_tasks.py
remoulade/middleware/middleware.py
remoulade/middleware/pipelines.py
remoulade/middleware/prometheus.py
remoulade/middleware/retries.py
remoulade/middleware/shutdown.py
remoulade/middleware/threading.py
remoulade/middleware/time_limit.py
remoulade/middleware/worker_thread_logging.py
remoulade/rate_limits/__init__.py
remoulade-5.0.0.dist-info/licenses/COPYING
remoulade-5.0.0.dist-info/licenses/COPYING.LESSER
remoulade-5.0.0.dist-info/METADATA
remoulade-5.0.0.dist-info/WHEEL
remoulade-5.0.0.dist-info/entry_points.txt
remoulade-5.0.0.dist-info/top_level.txt
remoulade-5.0.0.dist-info/RECORD
