Metadata-Version: 2.4
Name: remoulade
Version: 5.0.0
Summary: Background Processing for Python 3.
Author-email: Wiremind <dev@wiremind.io>
License-Expression: LGPL-3.0-or-later
Project-URL: Homepage, https://github.com/wiremind/remoulade
Project-URL: Documentation, https://remoulade.readthedocs.io/
Project-URL: Source, https://github.com/wiremind/remoulade
Project-URL: Tracker, https://github.com/wiremind/remoulade/issues
Classifier: Programming Language :: Python :: 3.12
Classifier: Programming Language :: Python :: 3.13
Classifier: Programming Language :: Python :: 3.14
Classifier: Programming Language :: Python :: 3 :: Only
Classifier: Topic :: System :: Distributed Computing
Requires-Python: >=3.12
License-File: COPYING
License-File: COPYING.LESSER
Requires-Dist: prometheus-client>=0.2
Requires-Dist: python-dateutil>=2.8.0
Requires-Dist: attrs>=19.2.0
Provides-Extra: rabbitmq
Requires-Dist: amqpstorm<3,>=2.6; extra == "rabbitmq"
Provides-Extra: redis
Requires-Dist: redis~=6.0; extra == "redis"
Provides-Extra: server
Requires-Dist: flask~=2.3.3; extra == "server"
Requires-Dist: marshmallow<4,>=3; extra == "server"
Requires-Dist: flask-apispec; extra == "server"
Provides-Extra: postgres
Requires-Dist: sqlalchemy<2,>=1.4.29; extra == "postgres"
Requires-Dist: psycopg2>=2.9.11; extra == "postgres"
Provides-Extra: pydantic
Requires-Dist: pydantic>=2.12; extra == "pydantic"
Requires-Dist: simplejson; extra == "pydantic"
Provides-Extra: limits
Requires-Dist: limits~=5.3.0; extra == "limits"
Provides-Extra: dev
Requires-Dist: amqpstorm<3,>=2.6; extra == "dev"
Requires-Dist: redis~=5.0; extra == "dev"
Requires-Dist: flask~=2.3.3; extra == "dev"
Requires-Dist: marshmallow<4,>=3; extra == "dev"
Requires-Dist: flask-apispec; extra == "dev"
Requires-Dist: sqlalchemy<2,>=1.4.29; extra == "dev"
Requires-Dist: psycopg2==2.9.10; extra == "dev"
Requires-Dist: pydantic>=2.12; extra == "dev"
Requires-Dist: simplejson; extra == "dev"
Requires-Dist: limits~=5.3.0; extra == "dev"
Requires-Dist: alabaster; extra == "dev"
Requires-Dist: sphinx==4.1.1; extra == "dev"
Requires-Dist: sphinxcontrib-napoleon; extra == "dev"
Requires-Dist: sphinxcontrib-versioning; extra == "dev"
Requires-Dist: sphinx-copybutton; extra == "dev"
Requires-Dist: ruff; extra == "dev"
Requires-Dist: mypy~=1.18.2; extra == "dev"
Requires-Dist: sqlalchemy[mypy]<2,>=1.4.29; extra == "dev"
Requires-Dist: types-redis; extra == "dev"
Requires-Dist: types-python-dateutil; extra == "dev"
Requires-Dist: types-simplejson; extra == "dev"
Requires-Dist: types-requests; extra == "dev"
Requires-Dist: pre-commit; extra == "dev"
Requires-Dist: hiredis; extra == "dev"
Requires-Dist: twine; extra == "dev"
Requires-Dist: pytest; extra == "dev"
Requires-Dist: pytest-benchmark[histogram]; extra == "dev"
Requires-Dist: pytest-cov; extra == "dev"
Requires-Dist: pytest-timeout; extra == "dev"
Requires-Dist: pytest-asyncio; extra == "dev"
Requires-Dist: freezegun; extra == "dev"
Dynamic: license-file
